certbot_dns_hotline/__init__.py
certbot_dns_hotline/dns_hotline.py
certbot_dns_hotline-0.4.0.dist-info/LICENSE
certbot_dns_hotline-0.4.0.dist-info/METADATA
certbot_dns_hotline-0.4.0.dist-info/WHEEL
certbot_dns_hotline-0.4.0.dist-info/entry_points.txt
certbot_dns_hotline-0.4.0.dist-info/top_level.txt
certbot_dns_hotline-0.4.0.dist-info/RECORD
