Metadata-Version: 2.1
Name: certbot-dns-hotline
Version: 0.4.0
Summary: Certbot DNS plugin for Hotline
Home-page: https://github.com/captainGeech42/certbot-dns-hotline
Author: Zander Work
Author-email: pypi@zanderwork.com
License: MIT
Platform: UNKNOWN
Classifier: License :: OSI Approved :: MIT License
Classifier: Programming Language :: Python :: 3
Requires-Python: >=3.6
Requires-Dist: certbot (==1.22.0)
